aws_sqs_batch_sender/__init__.py
aws_sqs_batch_sender/batch_sender.py
aws_sqs_batch_sender-1.0.0b1.dist-info/METADATA
aws_sqs_batch_sender-1.0.0b1.dist-info/WHEEL
aws_sqs_batch_sender-1.0.0b1.dist-info/top_level.txt
aws_sqs_batch_sender-1.0.0b1.dist-info/RECORD
