Metadata-Version: 2.1
Name: aws-sqs-batch-sender
Version: 1.0.0b1
Summary: AWS SQS Batch Sender for boto3
Home-page: https://github.com/cbuschka/aws-sqs-batch-sender-python
Author: Cornelius Buschka
Author-email: cbuschka@gmail.com
License: UNKNOWN
Platform: UNKNOWN
Classifier: Development Status :: 3 - Alpha
Classifier: Intended Audience :: Developers
Classifier: License :: OSI Approved :: MIT License
Classifier: Operating System :: OS Independent
Classifier: Programming Language :: Python :: 3
Classifier: Programming Language :: Python :: 3.6
Classifier: Programming Language :: Python :: 3.7
Classifier: Programming Language :: Python :: 3.8
Classifier: Programming Language :: Python :: 3.9
Classifier: Topic :: Software Development
Requires-Python: >=3.6
Requires-Dist: boto3 (>=1.19.2)
